customAdmin/__init__.py
customAdmin/admin.py
customAdmin/apps.py
customAdmin/models.py
customAdmin/tests.py
customAdmin/views.py
customAdmin/migrations/__init__.py
customAdmin/templates/admin/base_site.html
customAdmin/templates/admin/login.html
django_Admincustom-0.0.1.dist-info/LICENSE
django_Admincustom-0.0.1.dist-info/METADATA
django_Admincustom-0.0.1.dist-info/WHEEL
django_Admincustom-0.0.1.dist-info/top_level.txt
django_Admincustom-0.0.1.dist-info/RECORD
