Metadata-Version: 2.1
Name: django-Admincustom
Version: 0.0.1
Summary: Custom Admin Dashboard Interface
Home-page: UNKNOWN
Author: Jannat Ferdousey Tuba
Author-email: jannatferdouseytuba@gmail.com
License: MIT
Keywords: django,admin
Platform: UNKNOWN
Classifier: Environment :: Web Environment
Classifier: Framework :: Django
Classifier: Intended Audience :: Developers
Classifier: Programming Language :: Python :: 3
Classifier: License :: OSI Approved :: MIT License
Classifier: Operating System :: OS Independent
Classifier: Topic :: Software Development :: Libraries :: Python Modules
